[
  {
    "Invoice": 528368,
    "Product_ID": 22444,
    "Description": "GROW YOUR OWN PLANT IN A CAN ",
    "Quantity": 24,
    "Date": "2010-10-21",
    "Price": 1.25,
    "Customer ID": 13581,
    "Country": "United Kingdom",
    "Category": "Outdoor & Gardening"
  },
  {
    "Invoice": 528368,
    "Product_ID": "84845D",
    "Description": "GERANIUM SQUARE HANDY TIN",
    "Quantity": 6,
    "Date": "2010-10-21",
    "Price": 1.25,
    "Customer ID": 13581,
    "Country": "United Kingdom",
    "Category": "Storage & Organization"
  },
  {
    "Invoice": 528368,
    "Product_ID": 21894,
    "Description": "POTTING SHED SEED ENVELOPES",
    "Quantity": 4,
    "Date": "2010-10-21",
    "Price": 1.25,
    "Customer ID": 13581,
    "Country": "United Kingdom",
    "Category": "Outdoor & Gardening"
  },
  {
    "Invoice": 528368,
    "Product_ID": 21380,
    "Description": "WOODEN HAPPY BIRTHDAY GARLAND",
    "Quantity": 4,
    "Date": "2010-10-21",
    "Price": 2.95,
    "Customer ID": 13581,
    "Country": "United Kingdom",
    "Category": "Home Decor & Ornaments"
  },
  {
    "Invoice": 528368,
    "Product_ID": 21895,
    "Description": "POTTING SHED SOW 'N' GROW SET",
    "Quantity": 4,
    "Date": "2010-10-21",
    "Price": 4.25,
    "Customer ID": 13581,
    "Country": "United Kingdom",
    "Category": "Outdoor & Gardening"
  },
  {
    "Invoice": 528368,
    "Product_ID": 21610,
    "Description": "SET 12 PEAR BOTANICAL T-LIGHTS",
    "Quantity": 4,
    "Date": "2010-10-21",
    "Price": 2.95,
    "Customer ID": 13581,
    "Country": "United Kingdom",
    "Category": "Toys & Games"
  },
  {
    "Invoice": 528368,
    "Product_ID": 22567,
    "Description": "20 DOLLY PEGS RETROSPOT",
    "Quantity": 4,
    "Date": "2010-10-21",
    "Price": 1.25,
    "Customer ID": 13581,
    "Country": "United Kingdom",
    "Category": "Kitchenware"
  },
  {
    "Invoice": 528368,
    "Product_ID": 21472,
    "Description": "LADYBIRD + BEE RAFFIA FOOD COVER",
    "Quantity": 2,
    "Date": "2010-10-21",
    "Price": 3.75,
    "Customer ID": 13581,
    "Country": "United Kingdom",
    "Category": "Storage & Organization"
  },
  {
    "Invoice": 528368,
    "Product_ID": 22750,
    "Description": "FELTCRAFT PRINCESS LOLA DOLL",
    "Quantity": 1,
    "Date": "2010-10-21",
    "Price": 3.75,
    "Customer ID": 13581,
    "Country": "United Kingdom",
    "Category": "Crafts & Hobbies"
  },
  {
    "Invoice": 528368,
    "Product_ID": 35832,
    "Description": "WOOLLY HAT SOCK GLOVE ADVENT STRING",
    "Quantity": 2,
    "Date": "2010-10-21",
    "Price": 2.95,
    "Customer ID": 13581,
    "Country": "United Kingdom",
    "Category": "Fashion & Apparel"
  },
  {
    "Invoice": 528368,
    "Product_ID": 22467,
    "Description": "GUMBALL COAT RACK",
    "Quantity": 2,
    "Date": "2010-10-21",
    "Price": 2.55,
    "Customer ID": 13581,
    "Country": "United Kingdom",
    "Category": "Pet Supplies"
  },
  {
    "Invoice": 528368,
    "Product_ID": 21212,
    "Description": "PACK OF 72 RETROSPOT CAKE CASES",
    "Quantity": 3,
    "Date": "2010-10-21",
    "Price": 0.55,
    "Customer ID": 13581,
    "Country": "United Kingdom",
    "Category": "Toys & Games"
  },
  {
    "Invoice": 528368,
    "Product_ID": 84992,
    "Description": "72 SWEETHEART FAIRY CAKE CASES",
    "Quantity": 3,
    "Date": "2010-10-21",
    "Price": 0.55,
    "Customer ID": 13581,
    "Country": "United Kingdom",
    "Category": "Crafts & Hobbies"
  },
  {
    "Invoice": 528368,
    "Product_ID": 22951,
    "Description": "60 CAKE CASES DOLLY GIRL DESIGN",
    "Quantity": 3,
    "Date": "2010-10-21",
    "Price": 0.55,
    "Customer ID": 13581,
    "Country": "United Kingdom",
    "Category": "Baking & Cookware"
  },
  {
    "Invoice": 528368,
    "Product_ID": 84991,
    "Description": "60 TEATIME FAIRY CAKE CASES",
    "Quantity": 3,
    "Date": "2010-10-21",
    "Price": 0.55,
    "Customer ID": 13581,
    "Country": "United Kingdom",
    "Category": "Home Decor & Ornaments"
  },
  {
    "Invoice": 528368,
    "Product_ID": "17109D",
    "Description": "FLOWER FAIRY INCENSE BOUQUET",
    "Quantity": 2,
    "Date": "2010-10-21",
    "Price": 1.69,
    "Customer ID": 13581,
    "Country": "United Kingdom",
    "Category": "Outdoor & Gardening"
  },
  {
    "Invoice": 528368,
    "Product_ID": 21121,
    "Description": "SET/10 RED POLKADOT PARTY CANDLES",
    "Quantity": 1,
    "Date": "2010-10-21",
    "Price": 1.25,
    "Customer ID": 13581,
    "Country": "United Kingdom",
    "Category": "Color Themes"
  },
  {
    "Invoice": 528368,
    "Product_ID": 21896,
    "Description": "POTTING SHED TWINE",
    "Quantity": 2,
    "Date": "2010-10-21",
    "Price": 2.1,
    "Customer ID": 13581,
    "Country": "United Kingdom",
    "Category": "Outdoor & Gardening"
  },
  {
    "Invoice": 528368,
    "Product_ID": 22441,
    "Description": "GROW YOUR OWN BASIL IN ENAMEL MUG",
    "Quantity": 4,
    "Date": "2010-10-21",
    "Price": 2.1,
    "Customer ID": 13581,
    "Country": "United Kingdom",
    "Category": "Crafts & Hobbies"
  },
  {
    "Invoice": 528368,
    "Product_ID": "84924D",
    "Description": "LA PALMIERA METAL SIGN CALENDAR",
    "Quantity": 3,
    "Date": "2010-10-21",
    "Price": 3.75,
    "Customer ID": 13581,
    "Country": "United Kingdom",
    "Category": "Baking & Cookware"
  },
  {
    "Invoice": 528368,
    "Product_ID": "82545A",
    "Description": "COGNAC AUX OEUFS METAL 1 HOOK",
    "Quantity": 5,
    "Date": "2010-10-21",
    "Price": 1.25,
    "Customer ID": 13581,
    "Country": "United Kingdom",
    "Category": "Baking & Cookware"
  },
  {
    "Invoice": 528368,
    "Product_ID": 79321,
    "Description": "CHILLI LIGHTS",
    "Quantity": 2,
    "Date": "2010-10-21",
    "Price": 4.95,
    "Customer ID": 13581,
    "Country": "United Kingdom",
    "Category": "Home Decor & Ornaments"
  },
  {
    "Invoice": 528368,
    "Product_ID": 21034,
    "Description": "REX CASH+CARRY JUMBO SHOPPER",
    "Quantity": 1,
    "Date": "2010-10-21",
    "Price": 0.95,
    "Customer ID": 13581,
    "Country": "United Kingdom",
    "Category": "Toys & Games"
  },
  {
    "Invoice": 543126,
    "Product_ID": 48129,
    "Description": "DOORMAT TOPIARY",
    "Quantity": 1,
    "Date": "2011-02-03",
    "Price": 7.95,
    "Customer ID": 13581,
    "Country": "United Kingdom",
    "Category": "Home Decor & Ornaments"
  },
  {
    "Invoice": 543126,
    "Product_ID": 21472,
    "Description": "LADYBIRD + BEE RAFFIA FOOD COVER",
    "Quantity": 1,
    "Date": "2011-02-03",
    "Price": 3.75,
    "Customer ID": 13581,
    "Country": "United Kingdom",
    "Category": "Storage & Organization"
  },
  {
    "Invoice": 543126,
    "Product_ID": 21937,
    "Description": "STRAWBERRY   PICNIC BAG",
    "Quantity": 1,
    "Date": "2011-02-03",
    "Price": 2.95,
    "Customer ID": 13581,
    "Country": "United Kingdom",
    "Category": "Outdoor & Gardening"
  },
  {
    "Invoice": 543126,
    "Product_ID": 21974,
    "Description": "SET OF 36 PAISLEY FLOWER DOILIES",
    "Quantity": 1,
    "Date": "2011-02-03",
    "Price": 1.45,
    "Customer ID": 13581,
    "Country": "United Kingdom",
    "Category": "Toys & Games"
  },
  {
    "Invoice": 543126,
    "Product_ID": 22399,
    "Description": "MAGNETS PACK OF 4 CHILDHOOD MEMORY",
    "Quantity": 6,
    "Date": "2011-02-03",
    "Price": 1.25,
    "Customer ID": 13581,
    "Country": "United Kingdom",
    "Category": "Home Decor & Ornaments"
  },
  {
    "Invoice": 543126,
    "Product_ID": "85123A",
    "Description": "WHITE HANGING HEART T-LIGHT HOLDER",
    "Quantity": 6,
    "Date": "2011-02-03",
    "Price": 2.95,
    "Customer ID": 13581,
    "Country": "United Kingdom",
    "Category": "Color Themes"
  },
  {
    "Invoice": 543126,
    "Product_ID": 22453,
    "Description": "MEASURING TAPE BABUSHKA BLUE",
    "Quantity": 4,
    "Date": "2011-02-03",
    "Price": 2.95,
    "Customer ID": 13581,
    "Country": "United Kingdom",
    "Category": "Stationery"
  },
  {
    "Invoice": 543126,
    "Product_ID": 22454,
    "Description": "MEASURING TAPE BABUSHKA RED",
    "Quantity": 4,
    "Date": "2011-02-03",
    "Price": 2.95,
    "Customer ID": 13581,
    "Country": "United Kingdom",
    "Category": "Stationery"
  },
  {
    "Invoice": 543126,
    "Product_ID": "47570B",
    "Description": "TEA TIME TABLE CLOTH",
    "Quantity": 2,
    "Date": "2011-02-03",
    "Price": 10.65,
    "Customer ID": 13581,
    "Country": "United Kingdom",
    "Category": "Kitchenware"
  },
  {
    "Invoice": 543126,
    "Product_ID": "15058C",
    "Description": "ICE CREAM DESIGN GARDEN PARASOL",
    "Quantity": 4,
    "Date": "2011-02-03",
    "Price": 7.95,
    "Customer ID": 13581,
    "Country": "United Kingdom",
    "Category": "Beauty & Care"
  }
]